one_sdk/__init__.py
one_sdk/app.py
one_sdk/client.py
one_sdk/error.py
one_sdk/handle_map.py
one_sdk/platform.py
one_sdk/sf_host.py
one_sdk/assets/core.wasm
one_sdk-1.0.0b14.dist-info/LICENSE
one_sdk-1.0.0b14.dist-info/METADATA
one_sdk-1.0.0b14.dist-info/WHEEL
one_sdk-1.0.0b14.dist-info/top_level.txt
one_sdk-1.0.0b14.dist-info/RECORD
