Metadata-Version: 2.2
Name: one-sdk
Version: 1.0.0b14
Summary: OneSDK is a universal API client which provides an unparalleled developer experience for every HTTP API
Author-email: Superface Team <hello@superface.ai>
Project-URL: Homepage, https://github.com/superfaceai/one-sdk/tree/main/packages/python_host
Project-URL: Bug Tracker, https://github.com/superfaceai/one-sdk/issues
Keywords: superface,api,client,sdk,one-sdk,ai,integrations
Requires-Python: >=3.8
License-File: LICENSE
Requires-Dist: Brotli~=1.0.9
Requires-Dist: certifi~=2023.5.7
Requires-Dist: charset-normalizer~=3.1.0
Requires-Dist: idna~=3.4
Requires-Dist: urllib3~=2.0.3
Requires-Dist: wasmtime~=13.0.0
